cursor_cli/__init__.py
cursor_cli/__main__.py
cursor_cli/formatter.py
cursor_cli/runner.py
cursor_cli/session.py
cursor_cli-0.1.12.dist-info/METADATA
cursor_cli-0.1.12.dist-info/WHEEL
cursor_cli-0.1.12.dist-info/entry_points.txt
cursor_cli-0.1.12.dist-info/top_level.txt
cursor_cli-0.1.12.dist-info/RECORD
