Metadata-Version: 2.4
Name: cursor-cli
Version: 0.1.12
Summary: A wrapper for cursor-agent with formatted output support
Author: veictry
License: MIT
Project-URL: Homepage, https://github.com/veictry/cursor-cli
Project-URL: Repository, https://github.com/veictry/cursor-cli
Project-URL: Issues, https://github.com/veictry/cursor-cli/issues
Keywords: cursor,agent,cli,wrapper
Classifier: Development Status :: 3 - Alpha
Classifier: Environment :: Console
Classifier: Intended Audience :: Developers
Classifier: License :: OSI Approved :: MIT License
Classifier: Operating System :: POSIX :: Linux
Classifier: Operating System :: MacOS :: MacOS X
Classifier: Programming Language :: Python :: 3
Classifier: Topic :: Software Development :: Libraries :: Python Modules
Classifier: Topic :: Utilities
Requires-Python: >=3.8
Provides-Extra: dev
Requires-Dist: pytest>=7.0; extra == "dev"
Requires-Dist: pytest-cov>=4.0; extra == "dev"
Requires-Dist: build>=1.0; extra == "dev"
Requires-Dist: twine>=4.0; extra == "dev"
Dynamic: requires-python
